assassin_api/__init__.py
assassin_api/api.py
assassin_api/decorators.py
assassin_api/exceptions.py
assassin_api/mapping_models.py
assassin_api/queries.py
assassin_api/session.py
assassin_api/validators.py
assassin_api-0.0.2.dist-info/LICENSE
assassin_api-0.0.2.dist-info/METADATA
assassin_api-0.0.2.dist-info/WHEEL
assassin_api-0.0.2.dist-info/top_level.txt
assassin_api-0.0.2.dist-info/RECORD
